prov2neo/__init__.py
prov2neo/cli.py
prov2neo/client.py
prov2neo/decode.py
prov2neo/encode.py
prov2neo-1.2.2.dist-info/LICENSE
prov2neo-1.2.2.dist-info/METADATA
prov2neo-1.2.2.dist-info/WHEEL
prov2neo-1.2.2.dist-info/entry_points.txt
prov2neo-1.2.2.dist-info/top_level.txt
prov2neo-1.2.2.dist-info/RECORD
