Metadata-Version: 2.1
Name: prov2neo
Version: 1.2.2
Summary: "Import W3C PROV documents into Neo4j using py2neo\'s OGM."
Home-page: https://github.com/DLR-SC/prov2neo
Author: Claas de Boer
Author-email: claas.deboer@dlr.de
Maintainer: Andreas Schreiber
Maintainer-email: andreas.schreiber@dlr.de
License: MIT
Keywords: w3c prov,neo4j,graph import
Classifier: Development Status :: 5 - Production/Stable
Classifier: Environment :: Console
Classifier: Intended Audience :: Science/Research
Classifier: License :: OSI Approved :: MIT License
Classifier: Programming Language :: Python
Classifier: Programming Language :: Python :: 3 :: Only
Classifier: Topic :: Scientific/Engineering
Classifier: Topic :: Software Development :: Libraries :: Python Modules
Classifier: Topic :: Database
Classifier: Topic :: Database :: Front-Ends
Requires-Python: >=3.8
License-File: LICENSE
Requires-Dist: py2neo (==2021.2.3)
Requires-Dist: prov (==2.0.0)
Requires-Dist: interchange
